md2wx/__init__.py
md2wx/__main__.py
md2wx/app.py
md2wx/styles.py
md2wx/static/css/_basic.css
md2wx/static/css/blue.css
md2wx/static/css/cyan.css
md2wx/static/css/rose.css
md2wx/static/js/script.js
md2wx/templates/wx.html
md2wx-0.1.1.dist-info/entry_points.txt
md2wx-0.1.1.dist-info/LICENSE
md2wx-0.1.1.dist-info/WHEEL
md2wx-0.1.1.dist-info/METADATA
md2wx-0.1.1.dist-info/RECORD
