Metadata-Version: 2.1
Name: md2wx
Version: 0.1.1
Summary: 将 Markdown 转换为可以一键发布的 HTML
Author-email: davycloud <dawei.si@qq.com>
Requires-Python: >=3.8
Classifier: License :: OSI Approved :: MIT License
Requires-Dist: Markdown >=3.3.0,<4.0.0
Requires-Dist: python-frontmatter
Project-URL: Home, https://github.com/davycloud/md2wx
